activity_py/__init__.py
activity_py/activity.py
activity_py/fix.py
activity_py/utils.py
activity.py-0.1b7.dist-info/LICENSE
activity.py-0.1b7.dist-info/METADATA
activity.py-0.1b7.dist-info/WHEEL
activity.py-0.1b7.dist-info/top_level.txt
activity.py-0.1b7.dist-info/RECORD
