Metadata-Version: 2.1
Name: activity.py
Version: 0.1b7
Summary: null
Home-page: https://github.com/sesh/activity.py
Author: Brenton Cleeland
License: Apache License, Version 2.0
Project-URL: Issues, https://github.com/sesh/activity.py/issues
Project-URL: CI, https://github.com/sesh/activity.py/actions
Project-URL: Changelog, https://github.com/sesh/activity.py/releases
Requires-Python: >=3.7
License-File: LICENSE
Requires-Dist: fitparse==1.2.0
Requires-Dist: python-dateutil<2.9
Requires-Dist: defusedxml==0.7.1
Provides-Extra: test
Requires-Dist: pytest; extra == "test"
